flask_ftscursor/__init__.py
flask_ftscursor/flask_ftscursor.py
Flask_FTSCursor-0.2.6.dist-info/LICENSE
Flask_FTSCursor-0.2.6.dist-info/METADATA
Flask_FTSCursor-0.2.6.dist-info/WHEEL
Flask_FTSCursor-0.2.6.dist-info/top_level.txt
Flask_FTSCursor-0.2.6.dist-info/RECORD
