Metadata-Version: 2.1
Name: Flask-FTSCursor
Version: 0.2.6
Summary: An extension to facilitate using FTSCursor with flask
Home-page: https://gitlab.com/aaylward/flask-ftscursor
Author: Anthony Aylward
Author-email: aaylward@salk.edu
License: MIT
Platform: any
Classifier: Environment :: Web Environment
Classifier: Intended Audience :: Developers
Classifier: License :: OSI Approved :: MIT License
Classifier: Operating System :: OS Independent
Classifier: Programming Language :: Python
Classifier: Framework :: Flask
Classifier: Topic :: Internet :: WWW/HTTP :: Dynamic Content
Classifier: Topic :: Software Development :: Libraries :: Python Modules
License-File: LICENSE
Requires-Dist: Flask
Requires-Dist: ftscursor
